dataf/__init__.py
dataf/abc_entity.py
dataf/arg_parser.py
dataf/base_entity.py
dataf/command_line.py
dataf/database_manager.py
dataf/database_singleton.py
dataf/flask_engine.py
dataf/logging_decorator.py
dataf/logging_filters.py
dataf/logging_handlers.py
dataf/logging_level.py
dataf/migration_engine.py
dataf/property.py
dataf/yaml_parser.py
dataf/templates/entry_points.py.mako
dataf/templates/settings_templates/__init__.py.mako
dataf/templates/settings_templates/database.yml.mako
dataf/templates/settings_templates/directory.yml.mako
dataf/templates/settings_templates/logging.yml.mako
dataf/templates/settings_templates/settings.py.mako
dataf/templates/settings_templates/swagger.yml.mako
dataf/templates/settings_templates/views.yml.mako
dataf/tests/__init__.py
dataf/tests/test_abc_entity.py
dataf/tests/test_arg_parser.py
dataf/tests/test_base_entity.py
dataf/tests/test_database_manager.py
dataf/tests/test_database_singleton.py
dataf/tests/test_flask_engine.py
dataf/tests/test_logging_decorator.py
dataf/tests/test_logging_filters.py
dataf/tests/test_logging_handlers.py
dataf/tests/test_logging_level.py
dataf/tests/test_migration_engine.py
dataf/tests/test_property.py
dataf/tests/test_yaml_parser.py
dataf-0.0.3.dist-info/METADATA
dataf-0.0.3.dist-info/RECORD
dataf-0.0.3.dist-info/WHEEL
dataf-0.0.3.dist-info/entry_points.txt
dataf-0.0.3.dist-info/top_level.txt
