Metadata-Version: 2.1
Name: dataf
Version: 0.0.3
Summary: Create project to manipulate data.
Home-page: https://github.com/BenjaminBoumendil/dataf
Author: Boumendil Benjamin
Author-email: benjamin.boumendil@gmail.com
License: UNKNOWN
Platform: UNKNOWN
Classifier: Programming Language :: Python :: 3.5
Classifier: Programming Language :: Python :: 3.6
Classifier: License :: OSI Approved :: MIT License
Classifier: Operating System :: OS Independent
Requires-Python: >=3.5
Requires-Dist: SQLAlchemy
Requires-Dist: PyYAML
Requires-Dist: slackclient
Requires-Dist: flask
Requires-Dist: flasgger
Requires-Dist: docutils
Requires-Dist: mako
Requires-Dist: alembic
